LICENSE
MANIFEST.in
README.rst
setup.py
tesseract.pxd
tesserocr.pyx
tesserocr_experiment.pyx
ocrd_fork_tesserocr.egg-info/PKG-INFO
ocrd_fork_tesserocr.egg-info/SOURCES.txt
ocrd_fork_tesserocr.egg-info/dependency_links.txt
ocrd_fork_tesserocr.egg-info/top_level.txt
tests/__init__.py
tests/eurotext.tif
tests/test_api.py