Metadata-Version: 1.1
Name: ocrd-fork-tesserocr
Version: 3.0.0rc1
Summary: A simple, Pillow-friendly, Python wrapper around tesseract-ocr API using Cython
Home-page: https://github.com/sirfz/tesserocr
Author: Fayez Zouheiry
Author-email: iamfayez@gmail.com
License: MIT
Keywords: Tesseract,tesseract-ocr,OCR,optical character recognition,PIL,Pillow,Cython
Platform: UNKNOWN
Classifier: Development Status :: 5 - Production/Stable
Classifier: Intended Audience :: Developers
Classifier: Topic :: Multimedia :: Graphics :: Capture :: Scanners
Classifier: Topic :: Multimedia :: Graphics :: Graphics Conversion
Classifier: Topic :: Scientific/Engineering :: Image Recognition
Classifier: License :: OSI Approved :: MIT License
Classifier: Operating System :: POSIX
Classifier: Programming Language :: Python :: 2.7
Classifier: Programming Language :: Python :: 3
Classifier: Programming Language :: Python :: 3.3
Classifier: Programming Language :: Python :: 3.4
Classifier: Programming Language :: Python :: 3.5
Classifier: Programming Language :: Python :: 3.6
Classifier: Programming Language :: Python :: Implementation :: CPython
Classifier: Programming Language :: Python :: Implementation :: PyPy
Classifier: Programming Language :: Cython
